{
  "project_info": {
    "project_number": "331363630141",
    "project_id": "ec463senproj",
    "storage_bucket": "ec463senproj.appspot.com"
  },
  "client": [
    {
      "client_info": {
        "mobilesdk_app_id": "1:331363630141:android:381c2ff027d0b5c0c3fe54",
        "android_client_info": {
          "package_name": "com.example.untitled"
        }
      },
      "oauth_client": [
        {
          "client_id": "331363630141-7s362fqspqiv1igag2podm4a14htakcc.apps.googleusercontent.com",
          "client_type": 3
        }
      ],
      "api_key": [
        {
          "current_key": "AIzaSyCaP-Prt3TZjwkkz7GVjWkuQW6C6SV58c4"
        }
      ],
      "services": {
        "appinvite_service": {
          "other_platform_oauth_client": [
            {
              "client_id": "331363630141-7s362fqspqiv1igag2podm4a14htakcc.apps.googleusercontent.com",
              "client_type": 3
            }
          ]
        }
      }
    }
  ],
  "configuration_version": "1"
}